pulumi_newrelic/__init__.py
pulumi_newrelic/_inputs.py
pulumi_newrelic/_utilities.py
pulumi_newrelic/account_management.py
pulumi_newrelic/alert_channel.py
pulumi_newrelic/alert_condition.py
pulumi_newrelic/alert_muting_rule.py
pulumi_newrelic/alert_policy.py
pulumi_newrelic/alert_policy_channel.py
pulumi_newrelic/api_access_key.py
pulumi_newrelic/browser_application.py
pulumi_newrelic/data_partition_rule.py
pulumi_newrelic/entity_tags.py
pulumi_newrelic/events_to_metrics_rule.py
pulumi_newrelic/get_account.py
pulumi_newrelic/get_alert_channel.py
pulumi_newrelic/get_alert_policy.py
pulumi_newrelic/get_application.py
pulumi_newrelic/get_authentication_domain.py
pulumi_newrelic/get_cloud_account.py
pulumi_newrelic/get_entity.py
pulumi_newrelic/get_group.py
pulumi_newrelic/get_key_transaction.py
pulumi_newrelic/get_notification_destination.py
pulumi_newrelic/get_obfuscation_expression.py
pulumi_newrelic/get_service_level_alert_helper.py
pulumi_newrelic/get_test_grok_pattern.py
pulumi_newrelic/get_user.py
pulumi_newrelic/group.py
pulumi_newrelic/infra_alert_condition.py
pulumi_newrelic/key_transaction.py
pulumi_newrelic/log_parsing_rule.py
pulumi_newrelic/monitor_downtime.py
pulumi_newrelic/notification_channel.py
pulumi_newrelic/notification_destination.py
pulumi_newrelic/nrql_alert_condition.py
pulumi_newrelic/nrql_drop_rule.py
pulumi_newrelic/obfuscation_expression.py
pulumi_newrelic/obfuscation_rule.py
pulumi_newrelic/one_dashboard.py
pulumi_newrelic/one_dashboard_json.py
pulumi_newrelic/one_dashboard_raw.py
pulumi_newrelic/outputs.py
pulumi_newrelic/pipeline_cloud_rule.py
pulumi_newrelic/provider.py
pulumi_newrelic/pulumi-plugin.json
pulumi_newrelic/py.typed
pulumi_newrelic/service_level.py
pulumi_newrelic/user.py
pulumi_newrelic/workflow.py
pulumi_newrelic/cloud/__init__.py
pulumi_newrelic/cloud/_inputs.py
pulumi_newrelic/cloud/aws_govcloud_integrations.py
pulumi_newrelic/cloud/aws_govcloud_link_account.py
pulumi_newrelic/cloud/aws_integrations.py
pulumi_newrelic-5.58.0.dist-info/METADATA
pulumi_newrelic-5.58.0.dist-info/WHEEL
pulumi_newrelic-5.58.0.dist-info/top_level.txt
pulumi_newrelic-5.58.0.dist-info/RECORD
